livereload/__init__.py
livereload/cli.py
livereload/handlers.py
livereload/server.py
livereload/watcher.py
livereload/management/commands/__init__.py
livereload/management/commands/livereload.py
livereload/vendors/livereload.js
livereload-2.6.1.dist-info/LICENSE
livereload-2.6.1.dist-info/METADATA
livereload-2.6.1.dist-info/WHEEL
livereload-2.6.1.dist-info/entry_points.txt
livereload-2.6.1.dist-info/top_level.txt
livereload-2.6.1.dist-info/RECORD
